fireframe/__init__.py
fireframe/cli/__init__.py
fireframe/cli/project.py
fireframe/core/__init__.py
fireframe/core/api.py
fireframe/core/models.py
fireframe/core/serializers.py
fireframe/core/views.py
fireframe/core/viewsets.py
FireFrame-0.0.0a10.dist-info/LICENSE
FireFrame-0.0.0a10.dist-info/METADATA
FireFrame-0.0.0a10.dist-info/WHEEL
FireFrame-0.0.0a10.dist-info/entry_points.txt
FireFrame-0.0.0a10.dist-info/top_level.txt
FireFrame-0.0.0a10.dist-info/RECORD
